dacutil/__init__.py
dacutil/addict.py
dacutil/config.py
dacutil/crypt.py
dacutil/dateutil.py
dacutil/pyencryption.py
dacutil/strutil.py
dacutil/thai_mod11.py
dacutil/worker.py
dacutil-0.4.4.dist-info/METADATA
dacutil-0.4.4.dist-info/WHEEL
dacutil-0.4.4.dist-info/RECORD
