Metadata-Version: 2.1
Name: dacutil
Version: 0.4.4
Summary: Function Tools For Data Analytic
Author: Attapon Thanawong
Author-email: attapon_srem@hotmail.com
Requires-Python: >=3.9,<4.0
Classifier: Programming Language :: Python :: 3
Classifier: Programming Language :: Python :: 3.9
Classifier: Programming Language :: Python :: 3.10
Classifier: Programming Language :: Python :: 3.11
Classifier: Programming Language :: Python :: 3.12
Requires-Dist: configobj (>=5.0.0)
Requires-Dist: cryptography (>=41.0.0)
Requires-Dist: pandas (>=2.1.0)
Requires-Dist: pyarrow (>=14.0.0)
Requires-Dist: pycryptodome (>=3.17.0)
Requires-Dist: pyrage (>=1.1.0)
Requires-Dist: pyyaml (>=6.0.0)
Requires-Dist: requests (>=2.31.0)
Requires-Dist: tomli (>=2.0.0)
